nightjarpy/__init__.py
nightjarpy/__main__.py
nightjarpy/compilation/__init__.py
nightjarpy/compilation/compile.py
nightjarpy/compilation/utils.py
nightjarpy/configs.py
nightjarpy/context.py
nightjarpy/decorators.py
nightjarpy/effects.py
nightjarpy/llm/__init__.py
nightjarpy/llm/base.py
nightjarpy/llm/clients/__init__.py
nightjarpy/llm/clients/anthropic.py
nightjarpy/llm/clients/openai.py
nightjarpy/llm/factory.py
nightjarpy/prompts/__init__.py
nightjarpy/prompts/base.py
nightjarpy/prompts/prompts.py
nightjarpy/runtime/__init__.py
nightjarpy/runtime/run.py
nightjarpy/types.py
nightjarpy/utils/__init__.py
nightjarpy/utils/cache.py
nightjarpy/utils/utils.py
nightjarpy-0.1.0.dist-info/METADATA
nightjarpy-0.1.0.dist-info/WHEEL
nightjarpy-0.1.0.dist-info/licenses/LICENSE
nightjarpy-0.1.0.dist-info/RECORD
