Metadata-Version: 2.4
Name: nightjarpy
Version: 0.1.0
Summary: Python library for embedding natural language code with shared program state in Python programs
License: MIT License
License-File: LICENSE
Keywords: natural language programming,llm,interoperability
Author: Ellie Cheng
Author-email: ellieyhc@csail.mit.edu
Requires-Python: >=3.10
Classifier: Development Status :: 3 - Alpha
Classifier: Intended Audience :: Science/Research
Classifier: License :: OSI Approved :: MIT License
Classifier: Operating System :: OS Independent
Classifier: Programming Language :: Python :: 3
Classifier: Topic :: Software Development
Classifier: Topic :: Software Development :: Libraries
Classifier: Topic :: Scientific/Engineering
Classifier: Topic :: Scientific/Engineering :: Artificial Intelligence
Provides-Extra: all
Provides-Extra: research
Provides-Extra: viz
Provides-Extra: vllm
Requires-Dist: anthropic (>=0.74.0)
Requires-Dist: datasets (>=4.4.1) ; extra == "research"
Requires-Dist: dspy (>=3.0.0)
Requires-Dist: func-timeout (>=4.3.0)
Requires-Dist: nightjarpy[dev,research,viz,vllm] ; extra == "all"
Requires-Dist: numpy (>=2.2.2)
Requires-Dist: openai (>=2.8.1)
Requires-Dist: orjson (>=3.11.4)
Requires-Dist: pandas (>=2.2.3) ; extra == "research"
Requires-Dist: pandas (>=2.2.3) ; extra == "viz"
Requires-Dist: plotly (>=5.15.0) ; extra == "viz"
Requires-Dist: pydantic (>=2.12.5)
Requires-Dist: python-dotenv (>=1.0.1)
Requires-Dist: seaborn (>=0.13.2) ; extra == "research"
Requires-Dist: shortuuid (>=1.0.1)
Requires-Dist: streamlit (>=1.28.0) ; extra == "viz"
Requires-Dist: tabulate (>=0.9.0) ; extra == "research"
Requires-Dist: tqdm (>=4.62.3) ; extra == "research"
Requires-Dist: typed-argument-parser (>=1.10.0)
Requires-Dist: typeguard (>=3.0.0)
Requires-Dist: vllm ; extra == "vllm"
Requires-Dist: wandb (>=0.18.0) ; extra == "research"
Project-URL: Homepage, https://github.com/psg-mit/nightjarpy
Project-URL: Issues, https://github.com/psg-mit/nightjarpy/issues
